fantasia/__init__.py
fantasia/config.yaml
fantasia/constants.yaml
fantasia/main.py
fantasia/src/__init__.py
fantasia/src/embedder.py
fantasia/src/helpers/__init__.py
fantasia/src/helpers/helpers.py
fantasia/src/helpers/parser.py
fantasia/src/lookup.py
fantasia-4.1.0.dist-info/LICENSE
fantasia-4.1.0.dist-info/METADATA
fantasia-4.1.0.dist-info/WHEEL
fantasia-4.1.0.dist-info/entry_points.txt
fantasia-4.1.0.dist-info/RECORD
