Metadata-Version: 2.1
Name: fantasia
Version: 4.1.0
Summary: Functional ANnoTAtion based on embedding space SImilArity
Author: Francisco Miguel Pérez Canales
Author-email: frapercan1@alum.us.es
Requires-Python: >=3.12,<4.0
Classifier: Programming Language :: Python :: 3
Requires-Dist: docopt (>=0.6.2,<0.7.0)
Requires-Dist: ete3 (>=3.1.3,<4.0.0)
Requires-Dist: goatools (>=1.4.12,<2.0.0)
Requires-Dist: numpy (>=2.3.4,<3.0.0)
Requires-Dist: parasail (>=1.3.4,<2.0.0)
Requires-Dist: polars (>=1.33.1,<2.0.0)
Requires-Dist: protein-information-system (>=3.1.0,<4.0.0)
Requires-Dist: pyarrow (>=21.0.0,<22.0.0)
Requires-Dist: scipy (>=1.16.0,<2.0.0)
